finn_finder/__init__.py
finn_finder-0.0.0.dist-info/METADATA
finn_finder-0.0.0.dist-info/WHEEL
finn_finder-0.0.0.dist-info/top_level.txt
finn_finder-0.0.0.dist-info/RECORD
