Metadata-Version: 2.1
Name: finn-finder
Version: 0.0.0
Summary: An application for advanced filtering of finn.no listings
Author-email: Magnus Kristiansen <magnuskri99@gmail.com>
Classifier: Development Status :: 1 - Planning
